wxapis/__init__.py
wxapis/abstract.py
wxapis/corporate.py
wxapis/medias.py
wxapis/smsg.py
wxapis-2.0.0.dist-info/LICENSE
wxapis-2.0.0.dist-info/METADATA
wxapis-2.0.0.dist-info/WHEEL
wxapis-2.0.0.dist-info/entry_points.txt
wxapis-2.0.0.dist-info/top_level.txt
wxapis-2.0.0.dist-info/RECORD
