Metadata-Version: 2.1
Name: wxapis
Version: 2.0.0
Summary: 企业微信服务端 API 操作库。
Home-page: https://github.com/gary714/wxapis
Author: gary
Author-email: mepmb@sina.com
License: MIT
Project-URL: Homepage, https://github.com/gary714/wxapis
Project-URL: Documentation, https://github.com/gary714/wxapis
Project-URL: Source, https://github.com/gary714/wxapis
Keywords: WeChat,WxWork
Platform: Linux
Platform: Windows
Classifier: License :: OSI Approved :: MIT License
Classifier: Programming Language :: Python :: 3.6
Classifier: Programming Language :: Python :: 3.7
Classifier: Programming Language :: Python :: 3.8
Classifier: Programming Language :: Python :: 3.9
Requires-Dist: flatten-dict (~=0.4.2)
Requires-Dist: PyYAML (~=6.0)
Requires-Dist: dict-recursive-update (~=1.0.1)
Requires-Dist: requests (~=2.32.3)
Requires-Dist: diskcache (~=5.4.0)
